Metadata-Version: 2.1
Name: feefkodhyionffu
Version: 0.1
Summary: A harmless package to prevent exploitation
Home-page: UNKNOWN
Author: hhttddggee
Author-email: hhttddggee@protonmail.com
License: UNKNOWN
Platform: UNKNOWN
